nonebot_plugin_addFriend/__init__.py
nonebot_plugin_addFriend/config.json
nonebot_plugin_addFriend/configUtil.py
nonebot_plugin_addFriend/num.json
nonebot_plugin_addFriend/requestor.json
nonebot_plugin_addFriend/utils.py
nonebot_plugin_addfriend-2.5.6.dist-info/LICENSE
nonebot_plugin_addfriend-2.5.6.dist-info/METADATA
nonebot_plugin_addfriend-2.5.6.dist-info/WHEEL
nonebot_plugin_addfriend-2.5.6.dist-info/RECORD
