Metadata-Version: 2.1
Name: nonebot-plugin-addfriend
Version: 2.5.6
Summary: 一个基于NoneBot2的插件，用于处理被请求加QQ好友和QQ群的请求.A plugin based on nonebot2, which is used to process requests to add QQ friends and QQ requests.
License: MIT
Author: ziru-w
Author-email: 77319678+ziru-w@users.noreply.github.com
Requires-Python: >=3.7,<4.0
Classifier: License :: OSI Approved :: MIT License
Classifier: Programming Language :: Python :: 3
Classifier: Programming Language :: Python :: 3.7
Classifier: Programming Language :: Python :: 3.8
Classifier: Programming Language :: Python :: 3.9
Classifier: Programming Language :: Python :: 3.10
Classifier: Programming Language :: Python :: 3.11
Requires-Dist: nonebot-adapter-onebot (>=2.0.0-beta.1)
Requires-Dist: nonebot2 (>=2.0.0-beta.1)
